cinefolders/__init__.py
cinefolders/__main__.py
cinefolders/cinefolders.py
cinefolders/organizer.py
cinefolders/tmdb/__init__.py
cinefolders/tmdb/episode.py
cinefolders/tmdb/exceptions.py
cinefolders/tmdb/item.py
cinefolders/tmdb/movie.py
cinefolders/tmdb/tmdb.py
cinefolders-0.0.9.dist-info/LICENSE
cinefolders-0.0.9.dist-info/METADATA
cinefolders-0.0.9.dist-info/WHEEL
cinefolders-0.0.9.dist-info/entry_points.txt
cinefolders-0.0.9.dist-info/top_level.txt
cinefolders-0.0.9.dist-info/RECORD
