Metadata-Version: 2.1
Name: cinefolders
Version: 0.0.9
Summary: A utility for organizing a media folder
Home-page: https://github.com/hgibs/cinefolders
Author: Holland Gibson
Author-email: cinefiles-hgibs@googlegroups.com
License: UNKNOWN
Platform: UNKNOWN
Classifier: Programming Language :: Python :: 3
Classifier: License :: OSI Approved :: Apache Software License
Classifier: Operating System :: OS Independent
Classifier: Development Status :: 2 - Pre-Alpha
Requires-Python: >=3.6
Requires-Dist: guessit (>=3.1)
Requires-Dist: requests (>=2.22)
Requires-Dist: pycountry (>=19.8.18)
Requires-Dist: argparse (>=1.4)
